ericnuno/__init__.py
ericnuno-0.60.dist-info/LICENSE
ericnuno-0.60.dist-info/METADATA
ericnuno-0.60.dist-info/WHEEL
ericnuno-0.60.dist-info/top_level.txt
ericnuno-0.60.dist-info/RECORD
