Metadata-Version: 2.1
Name: ericnuno
Version: 0.60
Summary: Erics common functions
Home-page: https://github.com/kingmold/ericnuno
Author: Eric Nuno
Author-email: ericnuno@gmail.com
License: MIT
Platform: UNKNOWN
Classifier: Programming Language :: Python :: 3
Classifier: License :: OSI Approved :: MIT License
Classifier: Operating System :: OS Independent
Requires-Dist: requests
Requires-Dist: paramiko
Requires-Dist: bs4
Requires-Dist: serial
Requires-Dist: pyserial
